AUTHORS.rst
HISTORY.rst
INSTALL
LICENSE
MANIFEST.in
README.rst
TODO
distribute_setup.py
setup.py
examples/pygacsExample.py
examples/pygacsExample_basic copy.py
examples/pygacsExample_publicAccess.py
pygacs/__init__.py
pygacs.egg-info/PKG-INFO
pygacs.egg-info/SOURCES.txt
pygacs.egg-info/dependency_links.txt
pygacs.egg-info/requires.txt
pygacs.egg-info/top_level.txt
pygacs/authen/__init__.py
pygacs/authen/manip.py
pygacs/public/__init__.py
pygacs/public/publicAccessTools.py