Metadata-Version: 1.1
Name: pygacs
Version: 0.2.8
Summary: Toolkit to access and manipulate Gaia catalogue tables hosted at ESA's Gaia Archive Core Systems (GACS)
Home-page: https://github.com/Johannes-Sahlmann/pygacs
Author: Johannes Sahlmann
Author-email: Johannes.Sahlmann@esa.int
License: LGPLv3+
Platform: UNKNOWN
Classifier: Development Status :: 2 - Pre-Alpha
Classifier: Intended Audience :: Developers
Classifier: Intended Audience :: Science/Research
Classifier: License :: OSI Approved :: GNU Lesser General Public License v3 or later (LGPLv3+)
Classifier: Operating System :: OS Independent
Classifier: Programming Language :: Python
Classifier: Topic :: Scientific/Engineering :: Astronomy
